confluent/__init__.py
confluent/schemaregistry/__init__.py
confluent/schemaregistry/client/CachedSchemaRegistryClient.py
confluent/schemaregistry/client/MockSchemaRegistryClient.py
confluent/schemaregistry/client/__init__.py
confluent/schemaregistry/serializers/MessageSerializer.py
confluent/schemaregistry/serializers/Util.py
confluent/schemaregistry/serializers/__init__.py
rpm_confluent_schemaregistry-0.1.1.dist-info/DESCRIPTION.rst
rpm_confluent_schemaregistry-0.1.1.dist-info/METADATA
rpm_confluent_schemaregistry-0.1.1.dist-info/RECORD
rpm_confluent_schemaregistry-0.1.1.dist-info/WHEEL
rpm_confluent_schemaregistry-0.1.1.dist-info/metadata.json
rpm_confluent_schemaregistry-0.1.1.dist-info/top_level.txt
