Metadata-Version: 2.0
Name: rpm-confluent-schemaregistry
Version: 0.1.1
Summary: Confluent Schema Registry lib
Home-page: UNKNOWN
Author: Verisign
Author-email: vsrtc-dev@verisign.com
License: UNKNOWN
Keywords: This is a mirror of https://github.com/verisign/python-confluent-schemaregistry until that package is registered on PyPI.
Platform: UNKNOWN
Requires-Dist: avro
Provides-Extra: fastavro
Requires-Dist: fastavro; extra == 'fastavro'
